odoo/addons/fs_attachment_s3/README.rst
odoo/addons/fs_attachment_s3/__init__.py
odoo/addons/fs_attachment_s3/__manifest__.py
odoo/addons/fs_attachment_s3/i18n/fs_attachment_s3.pot
odoo/addons/fs_attachment_s3/i18n/it.po
odoo/addons/fs_attachment_s3/models/__init__.py
odoo/addons/fs_attachment_s3/models/fs_storage.py
odoo/addons/fs_attachment_s3/models/ir_attachment.py
odoo/addons/fs_attachment_s3/readme/CONFIGURE.md
odoo/addons/fs_attachment_s3/readme/CONTRIBUTORS.md
odoo/addons/fs_attachment_s3/readme/CREDITS.md
odoo/addons/fs_attachment_s3/readme/DESCRIPTION.md
odoo/addons/fs_attachment_s3/static/description/icon.png
odoo/addons/fs_attachment_s3/static/description/index.html
odoo/addons/fs_attachment_s3/tests/__init__.py
odoo/addons/fs_attachment_s3/tests/common.py
odoo/addons/fs_attachment_s3/tests/test_fs_attachment_s3.py
odoo/addons/fs_attachment_s3/views/fs_storage.xml
odoo_addon_fs_attachment_s3-19.0.1.1.0.3.dist-info/METADATA
odoo_addon_fs_attachment_s3-19.0.1.1.0.3.dist-info/WHEEL
odoo_addon_fs_attachment_s3-19.0.1.1.0.3.dist-info/top_level.txt
odoo_addon_fs_attachment_s3-19.0.1.1.0.3.dist-info/RECORD
