Metadata-Version: 2.1
Name: odoo-addon-fs_attachment_s3
Version: 19.0.1.1.0.3
Requires-Dist: fsspec[s3]
Requires-Dist: odoo-addon-fs_attachment==19.0.*
Requires-Dist: odoo==19.0.*
Summary: Store attachments into S3 complient filesystem
Home-page: https://github.com/OCA/storage
License: AGPL-3
Author: ACSONE SA/NV,Odoo Community Association (OCA)
Author-email: support@odoo-community.org
Classifier: Programming Language :: Python
Classifier: Framework :: Odoo
Classifier: Framework :: Odoo :: 19.0
Classifier: License :: OSI Approved :: GNU Affero General Public License v3
